checks/__init__.py
checks/entrypoint.py
checks/py.typed
checks/macro_checks/__init__.py
checks/macro_checks/macro_arguments_have_descriptions.py
checks/macro_checks/macro_arguments_match_manifest_vs_sql.py
checks/macro_checks/macros_have_descriptions.py
checks/model_checks/__init__.py
checks/model_checks/model_column_descriptions_are_consistent.py
checks/model_checks/model_column_names_match_manifest_vs_catalog.py
checks/model_checks/model_column_types_match_manifest_vs_catalog.py
checks/model_checks/model_columns_have_descriptions.py
checks/model_checks/model_columns_have_types.py
checks/model_checks/models_have_constraints.py
checks/model_checks/models_have_contracts.py
checks/model_checks/models_have_data_tests.py
checks/model_checks/models_have_descriptions.py
checks/model_checks/models_have_properties_file.py
checks/model_checks/models_have_tags.py
checks/model_checks/models_have_unit_tests.py
checks/source_checks/__init__.py
checks/source_checks/source_column_names_match_manifest_vs_catalog.py
checks/source_checks/source_column_types_match_manifest_vs_catalog.py
checks/source_checks/source_columns_have_descriptions.py
checks/source_checks/source_columns_have_types.py
checks/source_checks/sources_have_data_tests.py
checks/source_checks/sources_have_descriptions.py
dbt_review_assistant-1.0.4.dist-info/licenses/LICENSE
utils/__init__.py
utils/artifact_data.py
utils/check_abc.py
utils/check_arg_parser.py
utils/check_failure_messages.py
utils/config.py
utils/console_formatting.py
utils/py.typed
dbt_review_assistant-1.0.4.dist-info/METADATA
dbt_review_assistant-1.0.4.dist-info/WHEEL
dbt_review_assistant-1.0.4.dist-info/entry_points.txt
dbt_review_assistant-1.0.4.dist-info/top_level.txt
dbt_review_assistant-1.0.4.dist-info/RECORD
