Metadata-Version: 2.4
Name: dbt-review-assistant
Version: 1.0.4
Summary: Pre-commit hooks for dbt projects
Project-URL: Repository, https://github.com/dbt-review-assistant/dbt-review-assistant
Requires-Python: >=3.10
License-File: LICENSE
Requires-Dist: colorconsole>=0.8.0
Requires-Dist: jinja2>=3.1.6
Requires-Dist: jsonschema>=4.25.1
Requires-Dist: packaging>=25.0
Requires-Dist: prettytable>=3.16.0
Requires-Dist: pyyaml>=6.0.3
Dynamic: license-file
